{
  "scriptId": "332",
  "url": "file:///Users/tettuan/github/frontmatter-to-schema/tests/unit/domain/template/strategies.test.ts",
  "functions": [
    {
      "functionName": "",
      "ranges": [{ "startOffset": 0, "endOffset": 14112, "count": 1 }],
      "isBlockCoverage": true
    },
    {
      "functionName": "<instance_members_initializer>",
      "ranges": [{ "startOffset": 556, "endOffset": 585, "count": 6 }],
      "isBlockCoverage": true
    },
    {
      "functionName": "MockAIAnalyzer",
      "ranges": [{ "startOffset": 589, "endOffset": 745, "count": 6 }],
      "isBlockCoverage": true
    },
    {
      "functionName": "analyze",
      "ranges": [
        { "startOffset": 748, "endOffset": 1163, "count": 5 },
        { "startOffset": 796, "endOffset": 1048, "count": 2 },
        { "startOffset": 1048, "endOffset": 1162, "count": 3 }
      ],
      "isBlockCoverage": true
    },
    {
      "functionName": "",
      "ranges": [{ "startOffset": 1219, "endOffset": 5565, "count": 1 }],
      "isBlockCoverage": true
    },
    {
      "functionName": "",
      "ranges": [{ "startOffset": 1345, "endOffset": 2430, "count": 1 }],
      "isBlockCoverage": true
    },
    {
      "functionName": "",
      "ranges": [
        { "startOffset": 2496, "endOffset": 3655, "count": 1 },
        { "startOffset": 3533, "endOffset": 3637, "count": 0 }
      ],
      "isBlockCoverage": true
    },
    {
      "functionName": "",
      "ranges": [
        { "startOffset": 3713, "endOffset": 4593, "count": 1 },
        { "startOffset": 3812, "endOffset": 4589, "count": 0 }
      ],
      "isBlockCoverage": true
    },
    {
      "functionName": "",
      "ranges": [{ "startOffset": 4652, "endOffset": 5561, "count": 1 }],
      "isBlockCoverage": true
    },
    {
      "functionName": "",
      "ranges": [{ "startOffset": 5620, "endOffset": 8364, "count": 1 }],
      "isBlockCoverage": true
    },
    {
      "functionName": "",
      "ranges": [{ "startOffset": 5695, "endOffset": 6446, "count": 1 }],
      "isBlockCoverage": true
    },
    {
      "functionName": "",
      "ranges": [{ "startOffset": 6503, "endOffset": 7230, "count": 1 }],
      "isBlockCoverage": true
    },
    {
      "functionName": "",
      "ranges": [{ "startOffset": 7279, "endOffset": 8360, "count": 1 }],
      "isBlockCoverage": true
    },
    {
      "functionName": "analyze",
      "ranges": [{ "startOffset": 7347, "endOffset": 7676, "count": 1 }],
      "isBlockCoverage": true
    },
    {
      "functionName": "",
      "ranges": [{ "startOffset": 8423, "endOffset": 12068, "count": 1 }],
      "isBlockCoverage": true
    },
    {
      "functionName": "",
      "ranges": [{ "startOffset": 8498, "endOffset": 9347, "count": 1 }],
      "isBlockCoverage": true
    },
    {
      "functionName": "",
      "ranges": [{ "startOffset": 9416, "endOffset": 10383, "count": 1 }],
      "isBlockCoverage": true
    },
    {
      "functionName": "",
      "ranges": [{ "startOffset": 10442, "endOffset": 11581, "count": 1 }],
      "isBlockCoverage": true
    },
    {
      "functionName": "",
      "ranges": [{ "startOffset": 11639, "endOffset": 12064, "count": 1 }],
      "isBlockCoverage": true
    },
    {
      "functionName": "",
      "ranges": [{ "startOffset": 12118, "endOffset": 14109, "count": 1 }],
      "isBlockCoverage": true
    },
    {
      "functionName": "",
      "ranges": [
        { "startOffset": 12234, "endOffset": 12693, "count": 1 },
        { "startOffset": 12345, "endOffset": 12689, "count": 3 }
      ],
      "isBlockCoverage": true
    },
    {
      "functionName": "",
      "ranges": [{ "startOffset": 12748, "endOffset": 13327, "count": 1 }],
      "isBlockCoverage": true
    },
    {
      "functionName": "",
      "ranges": [{ "startOffset": 13391, "endOffset": 14105, "count": 1 }],
      "isBlockCoverage": true
    }
  ]
}
