{
  "scriptId": "335",
  "url": "file:///Users/tettuan/github/frontmatter-to-schema/src/infrastructure/template/file-template-repository.ts",
  "functions": [
    {
      "functionName": "",
      "ranges": [{ "startOffset": 0, "endOffset": 7779, "count": 1 }],
      "isBlockCoverage": true
    },
    {
      "functionName": "<instance_members_initializer>",
      "ranges": [{ "startOffset": 535, "endOffset": 560, "count": 4 }],
      "isBlockCoverage": true
    },
    {
      "functionName": "FileTemplateRepository",
      "ranges": [{ "startOffset": 564, "endOffset": 672, "count": 4 }],
      "isBlockCoverage": true
    },
    {
      "functionName": "load",
      "ranges": [
        { "startOffset": 675, "endOffset": 1660, "count": 39 },
        { "startOffset": 796, "endOffset": 866, "count": 28 },
        { "startOffset": 866, "endOffset": 1206, "count": 11 },
        { "startOffset": 1206, "endOffset": 1484, "count": 55 },
        { "startOffset": 1375, "endOffset": 1470, "count": 0 },
        { "startOffset": 1484, "endOffset": 1659, "count": 11 }
      ],
      "isBlockCoverage": true
    },
    {
      "functionName": "loadFromPath",
      "ranges": [
        { "startOffset": 1663, "endOffset": 4435, "count": 55 },
        { "startOffset": 1796, "endOffset": 1922, "count": 0 },
        { "startOffset": 1925, "endOffset": 1936, "count": 0 },
        { "startOffset": 2028, "endOffset": 2667, "count": 0 },
        { "startOffset": 2874, "endOffset": 3957, "count": 0 },
        { "startOffset": 4198, "endOffset": 4387, "count": 0 },
        { "startOffset": 4388, "endOffset": 4405, "count": 0 }
      ],
      "isBlockCoverage": true
    },
    {
      "functionName": "save",
      "ranges": [
        { "startOffset": 4438, "endOffset": 5387, "count": 19 },
        { "startOffset": 4566, "endOffset": 4573, "count": 0 },
        { "startOffset": 4600, "endOffset": 4607, "count": 0 },
        { "startOffset": 4924, "endOffset": 5383, "count": 0 }
      ],
      "isBlockCoverage": true
    },
    {
      "functionName": "exists",
      "ranges": [{ "startOffset": 5390, "endOffset": 5561, "count": 0 }],
      "isBlockCoverage": false
    },
    {
      "functionName": "list",
      "ranges": [{ "startOffset": 5564, "endOffset": 6647, "count": 0 }],
      "isBlockCoverage": false
    },
    {
      "functionName": "determineTemplateFormat",
      "ranges": [{ "startOffset": 6754, "endOffset": 7396, "count": 0 }],
      "isBlockCoverage": false
    },
    {
      "functionName": "getSupportedExtensions",
      "ranges": [{ "startOffset": 7460, "endOffset": 7601, "count": 0 }],
      "isBlockCoverage": false
    },
    {
      "functionName": "isSupportedExtension",
      "ranges": [{ "startOffset": 7663, "endOffset": 7776, "count": 0 }],
      "isBlockCoverage": false
    }
  ]
}
