{
  "scriptId": "332",
  "url": "file:///Users/tettuan/github/frontmatter-to-schema/tests/unit/application/BuildRegistryUseCase.test.ts",
  "functions": [
    {
      "functionName": "",
      "ranges": [{ "startOffset": 0, "endOffset": 15382, "count": 1 }],
      "isBlockCoverage": true
    },
    {
      "functionName": "<instance_members_initializer>",
      "ranges": [{ "startOffset": 586, "endOffset": 595, "count": 11 }],
      "isBlockCoverage": true
    },
    {
      "functionName": "MockFileReader",
      "ranges": [{ "startOffset": 599, "endOffset": 672, "count": 11 }],
      "isBlockCoverage": true
    },
    {
      "functionName": "readDirectory",
      "ranges": [{ "startOffset": 675, "endOffset": 822, "count": 10 }],
      "isBlockCoverage": true
    },
    {
      "functionName": "",
      "ranges": [{ "startOffset": 760, "endOffset": 782, "count": 14 }],
      "isBlockCoverage": true
    },
    {
      "functionName": "readFile",
      "ranges": [{ "startOffset": 825, "endOffset": 961, "count": 0 }],
      "isBlockCoverage": false
    },
    {
      "functionName": "exists",
      "ranges": [{ "startOffset": 964, "endOffset": 1055, "count": 0 }],
      "isBlockCoverage": false
    },
    {
      "functionName": "setMockFiles",
      "ranges": [{ "startOffset": 1058, "endOffset": 1111, "count": 10 }],
      "isBlockCoverage": true
    },
    {
      "functionName": "<instance_members_initializer>",
      "ranges": [{ "startOffset": 1192, "endOffset": 1208, "count": 11 }],
      "isBlockCoverage": true
    },
    {
      "functionName": "writeJson",
      "ranges": [{ "startOffset": 1212, "endOffset": 1308, "count": 9 }],
      "isBlockCoverage": true
    },
    {
      "functionName": "ensureDir",
      "ranges": [{ "startOffset": 1311, "endOffset": 1398, "count": 0 }],
      "isBlockCoverage": false
    },
    {
      "functionName": "getWrittenData",
      "ranges": [{ "startOffset": 1401, "endOffset": 1462, "count": 2 }],
      "isBlockCoverage": true
    },
    {
      "functionName": "getAllWrittenData",
      "ranges": [{ "startOffset": 1465, "endOffset": 1536, "count": 0 }],
      "isBlockCoverage": false
    },
    {
      "functionName": "clear",
      "ranges": [{ "startOffset": 1539, "endOffset": 1579, "count": 0 }],
      "isBlockCoverage": false
    },
    {
      "functionName": "<instance_members_initializer>",
      "ranges": [{ "startOffset": 1690, "endOffset": 1746, "count": 11 }],
      "isBlockCoverage": true
    },
    {
      "functionName": "extract",
      "ranges": [
        { "startOffset": 1750, "endOffset": 1983, "count": 13 },
        { "startOffset": 1808, "endOffset": 1834, "count": 0 },
        { "startOffset": 1865, "endOffset": 1907, "count": 0 }
      ],
      "isBlockCoverage": true
    },
    {
      "functionName": "setReturnFrontMatter",
      "ranges": [{ "startOffset": 1986, "endOffset": 2061, "count": 0 }],
      "isBlockCoverage": false
    },
    {
      "functionName": "setMockFrontMatter",
      "ranges": [{ "startOffset": 2064, "endOffset": 2141, "count": 0 }],
      "isBlockCoverage": false
    },
    {
      "functionName": "<instance_members_initializer>",
      "ranges": [{ "startOffset": 2242, "endOffset": 2283, "count": 11 }],
      "isBlockCoverage": true
    },
    {
      "functionName": "analyze",
      "ranges": [
        { "startOffset": 2287, "endOffset": 2764, "count": 7 },
        { "startOffset": 2350, "endOffset": 2399, "count": 0 },
        { "startOffset": 2470, "endOffset": 2605, "count": 0 }
      ],
      "isBlockCoverage": true
    },
    {
      "functionName": "setShouldSucceed",
      "ranges": [{ "startOffset": 2767, "endOffset": 2828, "count": 0 }],
      "isBlockCoverage": false
    },
    {
      "functionName": "setMockCommands",
      "ranges": [{ "startOffset": 2831, "endOffset": 2896, "count": 7 }],
      "isBlockCoverage": true
    },
    {
      "functionName": "createMockPromptFile",
      "ranges": [{ "startOffset": 2953, "endOffset": 3032, "count": 14 }],
      "isBlockCoverage": true
    },
    {
      "functionName": "createTestCommand",
      "ranges": [{ "startOffset": 3060, "endOffset": 3134, "count": 13 }],
      "isBlockCoverage": true
    },
    {
      "functionName": "fn",
      "ranges": [{ "startOffset": 3236, "endOffset": 15377, "count": 1 }],
      "isBlockCoverage": true
    },
    {
      "functionName": "setupMocks",
      "ranges": [{ "startOffset": 3417, "endOffset": 3774, "count": 11 }],
      "isBlockCoverage": true
    },
    {
      "functionName": "",
      "ranges": [{ "startOffset": 3850, "endOffset": 5352, "count": 1 }],
      "isBlockCoverage": true
    },
    {
      "functionName": "mockAnalyzer.analyze",
      "ranges": [
        { "startOffset": 4321, "endOffset": 4769, "count": 2 },
        { "startOffset": 4410, "endOffset": 4474, "count": 1 },
        { "startOffset": 4475, "endOffset": 4553, "count": 1 }
      ],
      "isBlockCoverage": true
    },
    {
      "functionName": "",
      "ranges": [{ "startOffset": 5413, "endOffset": 5737, "count": 1 }],
      "isBlockCoverage": true
    },
    {
      "functionName": "",
      "ranges": [{ "startOffset": 5798, "endOffset": 6768, "count": 1 }],
      "isBlockCoverage": true
    },
    {
      "functionName": "mockExtractor.extract",
      "ranges": [
        { "startOffset": 6260, "endOffset": 6428, "count": 2 },
        { "startOffset": 6325, "endOffset": 6427, "count": 1 }
      ],
      "isBlockCoverage": true
    },
    {
      "functionName": "",
      "ranges": [{ "startOffset": 6832, "endOffset": 7948, "count": 1 }],
      "isBlockCoverage": true
    },
    {
      "functionName": "mockAnalyzer.analyze",
      "ranges": [
        { "startOffset": 7334, "endOffset": 7559, "count": 2 },
        { "startOffset": 7405, "endOffset": 7558, "count": 1 }
      ],
      "isBlockCoverage": true
    },
    {
      "functionName": "",
      "ranges": [{ "startOffset": 8010, "endOffset": 9249, "count": 1 }],
      "isBlockCoverage": true
    },
    {
      "functionName": "mockAnalyzer.analyze",
      "ranges": [
        { "startOffset": 8507, "endOffset": 8882, "count": 2 },
        { "startOffset": 8580, "endOffset": 8881, "count": 1 }
      ],
      "isBlockCoverage": true
    },
    {
      "functionName": "",
      "ranges": [{ "startOffset": 9315, "endOffset": 10574, "count": 1 }],
      "isBlockCoverage": true
    },
    {
      "functionName": "mockAnalyzer.analyze",
      "ranges": [
        { "startOffset": 9723, "endOffset": 10195, "count": 2 },
        { "startOffset": 9790, "endOffset": 10187, "count": 1 }
      ],
      "isBlockCoverage": true
    },
    {
      "functionName": "",
      "ranges": [{ "startOffset": 10646, "endOffset": 11490, "count": 1 }],
      "isBlockCoverage": true
    },
    {
      "functionName": "",
      "ranges": [{ "startOffset": 11548, "endOffset": 12544, "count": 1 }],
      "isBlockCoverage": true
    },
    {
      "functionName": "",
      "ranges": [{ "startOffset": 12601, "endOffset": 13409, "count": 1 }],
      "isBlockCoverage": true
    },
    {
      "functionName": "",
      "ranges": [{ "startOffset": 13465, "endOffset": 14282, "count": 1 }],
      "isBlockCoverage": true
    },
    {
      "functionName": "readDirectory",
      "ranges": [{ "startOffset": 13598, "endOffset": 13685, "count": 1 }],
      "isBlockCoverage": true
    },
    {
      "functionName": "readFile",
      "ranges": [{ "startOffset": 13694, "endOffset": 13771, "count": 0 }],
      "isBlockCoverage": false
    },
    {
      "functionName": "exists",
      "ranges": [{ "startOffset": 13780, "endOffset": 13861, "count": 0 }],
      "isBlockCoverage": false
    },
    {
      "functionName": "",
      "ranges": [{ "startOffset": 14158, "endOffset": 14239, "count": 1 }],
      "isBlockCoverage": true
    },
    {
      "functionName": "",
      "ranges": [{ "startOffset": 14338, "endOffset": 15371, "count": 1 }],
      "isBlockCoverage": true
    },
    {
      "functionName": "writeJson",
      "ranges": [{ "startOffset": 14768, "endOffset": 14854, "count": 1 }],
      "isBlockCoverage": true
    },
    {
      "functionName": "ensureDir",
      "ranges": [{ "startOffset": 14863, "endOffset": 14948, "count": 0 }],
      "isBlockCoverage": false
    },
    {
      "functionName": "",
      "ranges": [{ "startOffset": 15245, "endOffset": 15332, "count": 1 }],
      "isBlockCoverage": true
    }
  ]
}
