{
  "scriptId": "332",
  "url": "file:///Users/tettuan/github/frontmatter-to-schema/tests/unit/infrastructure/adapters/mock-analyzer.test.ts",
  "functions": [
    {
      "functionName": "",
      "ranges": [{ "startOffset": 0, "endOffset": 17463, "count": 1 }],
      "isBlockCoverage": true
    },
    {
      "functionName": "createTestSchema",
      "ranges": [{ "startOffset": 464, "endOffset": 813, "count": 11 }],
      "isBlockCoverage": true
    },
    {
      "functionName": "getFields",
      "ranges": [{ "startOffset": 520, "endOffset": 733, "count": 0 }],
      "isBlockCoverage": false
    },
    {
      "functionName": "validate",
      "ranges": [{ "startOffset": 749, "endOffset": 806, "count": 0 }],
      "isBlockCoverage": false
    },
    {
      "functionName": "createTestFrontMatter",
      "ranges": [{ "startOffset": 814, "endOffset": 933, "count": 10 }],
      "isBlockCoverage": true
    },
    {
      "functionName": "getContent",
      "ranges": [{ "startOffset": 883, "endOffset": 926, "count": 10 }],
      "isBlockCoverage": true
    },
    {
      "functionName": "toJSON",
      "ranges": [{ "startOffset": 906, "endOffset": 917, "count": 10 }],
      "isBlockCoverage": true
    },
    {
      "functionName": "",
      "ranges": [{ "startOffset": 986, "endOffset": 2073, "count": 1 }],
      "isBlockCoverage": true
    },
    {
      "functionName": "",
      "ranges": [{ "startOffset": 1054, "endOffset": 1213, "count": 1 }],
      "isBlockCoverage": true
    },
    {
      "functionName": "",
      "ranges": [{ "startOffset": 1270, "endOffset": 1615, "count": 1 }],
      "isBlockCoverage": true
    },
    {
      "functionName": "",
      "ranges": [{ "startOffset": 1677, "endOffset": 1848, "count": 1 }],
      "isBlockCoverage": true
    },
    {
      "functionName": "",
      "ranges": [{ "startOffset": 1906, "endOffset": 2069, "count": 1 }],
      "isBlockCoverage": true
    },
    {
      "functionName": "",
      "ranges": [{ "startOffset": 2116, "endOffset": 5410, "count": 1 }],
      "isBlockCoverage": true
    },
    {
      "functionName": "",
      "ranges": [{ "startOffset": 2188, "endOffset": 2867, "count": 1 }],
      "isBlockCoverage": true
    },
    {
      "functionName": "",
      "ranges": [{ "startOffset": 2927, "endOffset": 3430, "count": 1 }],
      "isBlockCoverage": true
    },
    {
      "functionName": "",
      "ranges": [{ "startOffset": 3489, "endOffset": 3975, "count": 1 }],
      "isBlockCoverage": true
    },
    {
      "functionName": "",
      "ranges": [{ "startOffset": 4021, "endOffset": 4414, "count": 1 }],
      "isBlockCoverage": true
    },
    {
      "functionName": "",
      "ranges": [{ "startOffset": 4468, "endOffset": 4917, "count": 1 }],
      "isBlockCoverage": true
    },
    {
      "functionName": "",
      "ranges": [{ "startOffset": 4965, "endOffset": 5406, "count": 1 }],
      "isBlockCoverage": true
    },
    {
      "functionName": "",
      "ranges": [{ "startOffset": 5457, "endOffset": 10276, "count": 1 }],
      "isBlockCoverage": true
    },
    {
      "functionName": "",
      "ranges": [{ "startOffset": 5534, "endOffset": 6285, "count": 1 }],
      "isBlockCoverage": true
    },
    {
      "functionName": "",
      "ranges": [{ "startOffset": 6340, "endOffset": 6901, "count": 1 }],
      "isBlockCoverage": true
    },
    {
      "functionName": "",
      "ranges": [{ "startOffset": 6955, "endOffset": 8102, "count": 1 }],
      "isBlockCoverage": true
    },
    {
      "functionName": "",
      "ranges": [{ "startOffset": 8148, "endOffset": 8810, "count": 1 }],
      "isBlockCoverage": true
    },
    {
      "functionName": "",
      "ranges": [{ "startOffset": 8864, "endOffset": 9431, "count": 1 }],
      "isBlockCoverage": true
    },
    {
      "functionName": "",
      "ranges": [{ "startOffset": 9489, "endOffset": 10272, "count": 1 }],
      "isBlockCoverage": true
    },
    {
      "functionName": "",
      "ranges": [{ "startOffset": 10322, "endOffset": 12680, "count": 1 }],
      "isBlockCoverage": true
    },
    {
      "functionName": "",
      "ranges": [{ "startOffset": 10390, "endOffset": 11102, "count": 1 }],
      "isBlockCoverage": true
    },
    {
      "functionName": "JSON.stringify",
      "ranges": [{ "startOffset": 10736, "endOffset": 10789, "count": 1 }],
      "isBlockCoverage": true
    },
    {
      "functionName": "",
      "ranges": [{ "startOffset": 11164, "endOffset": 11868, "count": 1 }],
      "isBlockCoverage": true
    },
    {
      "functionName": "getContent",
      "ranges": [{ "startOffset": 11329, "endOffset": 11391, "count": 1 }],
      "isBlockCoverage": true
    },
    {
      "functionName": "",
      "ranges": [{ "startOffset": 11926, "endOffset": 12676, "count": 1 }],
      "isBlockCoverage": true
    },
    {
      "functionName": "ExtractedData.create",
      "ranges": [{ "startOffset": 12227, "endOffset": 12280, "count": 1 }],
      "isBlockCoverage": true
    },
    {
      "functionName": "",
      "ranges": [{ "startOffset": 12730, "endOffset": 14058, "count": 1 }],
      "isBlockCoverage": true
    },
    {
      "functionName": "",
      "ranges": [{ "startOffset": 12802, "endOffset": 13138, "count": 1 }],
      "isBlockCoverage": true
    },
    {
      "functionName": "",
      "ranges": [{ "startOffset": 13204, "endOffset": 13551, "count": 1 }],
      "isBlockCoverage": true
    },
    {
      "functionName": "",
      "ranges": [{ "startOffset": 13616, "endOffset": 14054, "count": 1 }],
      "isBlockCoverage": true
    },
    {
      "functionName": "",
      "ranges": [{ "startOffset": 14100, "endOffset": 17460, "count": 1 }],
      "isBlockCoverage": true
    },
    {
      "functionName": "",
      "ranges": [
        { "startOffset": 14163, "endOffset": 14577, "count": 1 },
        { "startOffset": 14292, "endOffset": 14345, "count": 1000 }
      ],
      "isBlockCoverage": true
    },
    {
      "functionName": "",
      "ranges": [{ "startOffset": 14636, "endOffset": 15211, "count": 1 }],
      "isBlockCoverage": true
    },
    {
      "functionName": "",
      "ranges": [
        { "startOffset": 15267, "endOffset": 16013, "count": 1 },
        { "startOffset": 15880, "endOffset": 16009, "count": 0 }
      ],
      "isBlockCoverage": true
    },
    {
      "functionName": "getContent",
      "ranges": [{ "startOffset": 15490, "endOffset": 15604, "count": 1 }],
      "isBlockCoverage": true
    },
    {
      "functionName": "toJSON",
      "ranges": [{ "startOffset": 15515, "endOffset": 15593, "count": 1 }],
      "isBlockCoverage": true
    },
    {
      "functionName": "",
      "ranges": [{ "startOffset": 16067, "endOffset": 16713, "count": 1 }],
      "isBlockCoverage": true
    },
    {
      "functionName": "",
      "ranges": [{ "startOffset": 16775, "endOffset": 17456, "count": 1 }],
      "isBlockCoverage": true
    },
    {
      "functionName": "",
      "ranges": [{ "startOffset": 16901, "endOffset": 17015, "count": 10 }],
      "isBlockCoverage": true
    },
    {
      "functionName": "",
      "ranges": [{ "startOffset": 17080, "endOffset": 17108, "count": 10 }],
      "isBlockCoverage": true
    },
    {
      "functionName": "",
      "ranges": [{ "startOffset": 17184, "endOffset": 17450, "count": 10 }],
      "isBlockCoverage": true
    }
  ]
}
