{
  "scriptId": "374",
  "url": "file:///Users/tettuan/github/frontmatter-to-schema/src/domain/models/template-entities.ts",
  "functions": [
    {
      "functionName": "",
      "ranges": [{ "startOffset": 0, "endOffset": 9468, "count": 1 }],
      "isBlockCoverage": true
    },
    {
      "functionName": "<instance_members_initializer>",
      "ranges": [{ "startOffset": 310, "endOffset": 315, "count": 20 }],
      "isBlockCoverage": true
    },
    {
      "functionName": "TemplateId",
      "ranges": [{ "startOffset": 319, "endOffset": 366, "count": 20 }],
      "isBlockCoverage": true
    },
    {
      "functionName": "create",
      "ranges": [
        { "startOffset": 376, "endOffset": 611, "count": 20 },
        { "startOffset": 431, "endOffset": 537, "count": 0 }
      ],
      "isBlockCoverage": true
    },
    {
      "functionName": "getValue",
      "ranges": [{ "startOffset": 614, "endOffset": 653, "count": 25 }],
      "isBlockCoverage": true
    },
    {
      "functionName": "equals",
      "ranges": [{ "startOffset": 656, "endOffset": 714, "count": 0 }],
      "isBlockCoverage": false
    },
    {
      "functionName": "<instance_members_initializer>",
      "ranges": [{ "startOffset": 762, "endOffset": 822, "count": 20 }],
      "isBlockCoverage": true
    },
    {
      "functionName": "Template",
      "ranges": [{ "startOffset": 826, "endOffset": 1054, "count": 20 }],
      "isBlockCoverage": true
    },
    {
      "functionName": "create",
      "ranges": [
        { "startOffset": 1064, "endOffset": 1634, "count": 20 },
        { "startOffset": 1254, "endOffset": 1508, "count": 0 }
      ],
      "isBlockCoverage": true
    },
    {
      "functionName": "createLegacy",
      "ranges": [
        { "startOffset": 1857, "endOffset": 2122, "count": 6 },
        { "startOffset": 2011, "endOffset": 2094, "count": 0 }
      ],
      "isBlockCoverage": true
    },
    {
      "functionName": "getId",
      "ranges": [{ "startOffset": 2125, "endOffset": 2158, "count": 25 }],
      "isBlockCoverage": true
    },
    {
      "functionName": "getFormat",
      "ranges": [{ "startOffset": 2161, "endOffset": 2202, "count": 13 }],
      "isBlockCoverage": true
    },
    {
      "functionName": "getMappingRules",
      "ranges": [{ "startOffset": 2205, "endOffset": 2258, "count": 0 }],
      "isBlockCoverage": false
    },
    {
      "functionName": "getDescription",
      "ranges": [{ "startOffset": 2261, "endOffset": 2312, "count": 0 }],
      "isBlockCoverage": false
    },
    {
      "functionName": "applyRules",
      "ranges": [{ "startOffset": 2315, "endOffset": 5202, "count": 0 }],
      "isBlockCoverage": false
    },
    {
      "functionName": "parseTemplateContent",
      "ranges": [{ "startOffset": 5288, "endOffset": 6070, "count": 0 }],
      "isBlockCoverage": false
    },
    {
      "functionName": "substituteTemplateValues",
      "ranges": [{ "startOffset": 6162, "endOffset": 6994, "count": 0 }],
      "isBlockCoverage": false
    },
    {
      "functionName": "getValueByPath",
      "ranges": [{ "startOffset": 7146, "endOffset": 7529, "count": 0 }],
      "isBlockCoverage": false
    },
    {
      "functionName": "setValueByPath",
      "ranges": [{ "startOffset": 7695, "endOffset": 9465, "count": 0 }],
      "isBlockCoverage": false
    }
  ]
}
