{
  "scriptId": "334",
  "url": "file:///Users/tettuan/github/frontmatter-to-schema/src/domain/analyzers/value-objects.ts",
  "functions": [
    {
      "functionName": "",
      "ranges": [{ "startOffset": 0, "endOffset": 6532, "count": 1 }],
      "isBlockCoverage": true
    },
    {
      "functionName": "<instance_members_initializer>",
      "ranges": [{ "startOffset": 370, "endOffset": 375, "count": 10 }],
      "isBlockCoverage": true
    },
    {
      "functionName": "RegistryVersion",
      "ranges": [{ "startOffset": 379, "endOffset": 426, "count": 10 }],
      "isBlockCoverage": true
    },
    {
      "functionName": "create",
      "ranges": [
        { "startOffset": 436, "endOffset": 859, "count": 14 },
        { "startOffset": 533, "endOffset": 780, "count": 10 },
        { "startOffset": 780, "endOffset": 858, "count": 4 }
      ],
      "isBlockCoverage": true
    },
    {
      "functionName": "createDefault",
      "ranges": [{ "startOffset": 869, "endOffset": 961, "count": 6 }],
      "isBlockCoverage": true
    },
    {
      "functionName": "getValue",
      "ranges": [{ "startOffset": 964, "endOffset": 1003, "count": 7 }],
      "isBlockCoverage": true
    },
    {
      "functionName": "toString",
      "ranges": [{ "startOffset": 1006, "endOffset": 1045, "count": 2 }],
      "isBlockCoverage": true
    },
    {
      "functionName": "<instance_members_initializer>",
      "ranges": [{ "startOffset": 1126, "endOffset": 1141, "count": 13 }],
      "isBlockCoverage": true
    },
    {
      "functionName": "ToolConfiguration",
      "ranges": [{ "startOffset": 1145, "endOffset": 1233, "count": 13 }],
      "isBlockCoverage": true
    },
    {
      "functionName": "create",
      "ranges": [
        { "startOffset": 1243, "endOffset": 2025, "count": 24 },
        { "startOffset": 1272, "endOffset": 1293, "count": 23 },
        { "startOffset": 1295, "endOffset": 1449, "count": 5 },
        { "startOffset": 1449, "endOffset": 1662, "count": 19 },
        { "startOffset": 1662, "endOffset": 1931, "count": 6 },
        { "startOffset": 1931, "endOffset": 2024, "count": 13 }
      ],
      "isBlockCoverage": true
    },
    {
      "functionName": "getName",
      "ranges": [{ "startOffset": 2028, "endOffset": 2065, "count": 13 }],
      "isBlockCoverage": true
    },
    {
      "functionName": "isEnabled",
      "ranges": [{ "startOffset": 2068, "endOffset": 2110, "count": 9 }],
      "isBlockCoverage": true
    },
    {
      "functionName": "<instance_members_initializer>",
      "ranges": [{ "startOffset": 2191, "endOffset": 2220, "count": 10 }],
      "isBlockCoverage": true
    },
    {
      "functionName": "RegistryCommand",
      "ranges": [{ "startOffset": 2224, "endOffset": 2355, "count": 10 }],
      "isBlockCoverage": true
    },
    {
      "functionName": "create",
      "ranges": [
        { "startOffset": 2365, "endOffset": 2943, "count": 19 },
        { "startOffset": 2411, "endOffset": 2417, "count": 17 },
        { "startOffset": 2418, "endOffset": 2424, "count": 16 },
        { "startOffset": 2426, "endOffset": 2602, "count": 4 },
        { "startOffset": 2602, "endOffset": 2624, "count": 15 },
        { "startOffset": 2624, "endOffset": 2652, "count": 14 },
        { "startOffset": 2654, "endOffset": 2818, "count": 5 },
        { "startOffset": 2818, "endOffset": 2942, "count": 10 }
      ],
      "isBlockCoverage": true
    },
    {
      "functionName": "createFromPath",
      "ranges": [
        { "startOffset": 2953, "endOffset": 4046, "count": 9 },
        { "startOffset": 3301, "endOffset": 3472, "count": 6 },
        { "startOffset": 3472, "endOffset": 3587, "count": 3 },
        { "startOffset": 3614, "endOffset": 3886, "count": 5 },
        { "startOffset": 3886, "endOffset": 4045, "count": 4 }
      ],
      "isBlockCoverage": true
    },
    {
      "functionName": "",
      "ranges": [{ "startOffset": 3430, "endOffset": 3456, "count": 18 }],
      "isBlockCoverage": true
    },
    {
      "functionName": "",
      "ranges": [
        { "startOffset": 3553, "endOffset": 3579, "count": 6 },
        { "startOffset": 3560, "endOffset": 3579, "count": 5 }
      ],
      "isBlockCoverage": true
    },
    {
      "functionName": "toJSON",
      "ranges": [{ "startOffset": 4049, "endOffset": 4176, "count": 2 }],
      "isBlockCoverage": true
    },
    {
      "functionName": "getC1",
      "ranges": [{ "startOffset": 4179, "endOffset": 4212, "count": 6 }],
      "isBlockCoverage": true
    },
    {
      "functionName": "getC2",
      "ranges": [{ "startOffset": 4215, "endOffset": 4248, "count": 6 }],
      "isBlockCoverage": true
    },
    {
      "functionName": "getC3",
      "ranges": [{ "startOffset": 4251, "endOffset": 4284, "count": 6 }],
      "isBlockCoverage": true
    },
    {
      "functionName": "getDescription",
      "ranges": [{ "startOffset": 4287, "endOffset": 4338, "count": 2 }],
      "isBlockCoverage": true
    },
    {
      "functionName": "<instance_members_initializer>",
      "ranges": [{ "startOffset": 4449, "endOffset": 4510, "count": 6 }],
      "isBlockCoverage": true
    },
    {
      "functionName": "AnalysisContext",
      "ranges": [{ "startOffset": 4514, "endOffset": 4741, "count": 6 }],
      "isBlockCoverage": true
    },
    {
      "functionName": "create",
      "ranges": [
        { "startOffset": 4751, "endOffset": 5360, "count": 9 },
        { "startOffset": 4840, "endOffset": 4998, "count": 1 },
        { "startOffset": 4998, "endOffset": 5024, "count": 8 },
        { "startOffset": 5024, "endOffset": 5068, "count": 7 },
        { "startOffset": 5070, "endOffset": 5231, "count": 2 },
        { "startOffset": 5231, "endOffset": 5359, "count": 6 }
      ],
      "isBlockCoverage": true
    },
    {
      "functionName": "getDocumentPath",
      "ranges": [{ "startOffset": 5363, "endOffset": 5416, "count": 2 }],
      "isBlockCoverage": true
    },
    {
      "functionName": "getFrontMatterData",
      "ranges": [{ "startOffset": 5419, "endOffset": 5478, "count": 2 }],
      "isBlockCoverage": true
    },
    {
      "functionName": "getSchemaData",
      "ranges": [{ "startOffset": 5481, "endOffset": 5530, "count": 1 }],
      "isBlockCoverage": true
    },
    {
      "functionName": "getTemplateData",
      "ranges": [{ "startOffset": 5533, "endOffset": 5586, "count": 1 }],
      "isBlockCoverage": true
    },
    {
      "functionName": "<instance_members_initializer>",
      "ranges": [{ "startOffset": 5656, "endOffset": 5687, "count": 5 }],
      "isBlockCoverage": true
    },
    {
      "functionName": "RegistryData",
      "ranges": [{ "startOffset": 5691, "endOffset": 5824, "count": 5 }],
      "isBlockCoverage": true
    },
    {
      "functionName": "create",
      "ranges": [{ "startOffset": 5834, "endOffset": 6050, "count": 5 }],
      "isBlockCoverage": true
    },
    {
      "functionName": "toJSON",
      "ranges": [{ "startOffset": 6053, "endOffset": 6305, "count": 1 }],
      "isBlockCoverage": true
    },
    {
      "functionName": "",
      "ranges": [{ "startOffset": 6266, "endOffset": 6285, "count": 1 }],
      "isBlockCoverage": true
    },
    {
      "functionName": "getVersion",
      "ranges": [{ "startOffset": 6308, "endOffset": 6351, "count": 1 }],
      "isBlockCoverage": true
    },
    {
      "functionName": "getDescription",
      "ranges": [{ "startOffset": 6354, "endOffset": 6405, "count": 1 }],
      "isBlockCoverage": true
    },
    {
      "functionName": "getAvailableConfigs",
      "ranges": [{ "startOffset": 6408, "endOffset": 6475, "count": 4 }],
      "isBlockCoverage": true
    },
    {
      "functionName": "getCommands",
      "ranges": [{ "startOffset": 6478, "endOffset": 6529, "count": 2 }],
      "isBlockCoverage": true
    }
  ]
}
