{
  "scriptId": "381",
  "url": "file:///Users/tettuan/github/frontmatter-to-schema/src/domain/models/property-path.ts",
  "functions": [
    {
      "functionName": "",
      "ranges": [{ "startOffset": 0, "endOffset": 7664, "count": 1 }],
      "isBlockCoverage": true
    },
    {
      "functionName": "<instance_members_initializer>",
      "ranges": [{ "startOffset": 425, "endOffset": 449, "count": 0 }],
      "isBlockCoverage": true
    },
    {
      "functionName": "PropertyPath",
      "ranges": [{ "startOffset": 453, "endOffset": 561, "count": 0 }],
      "isBlockCoverage": false
    },
    {
      "functionName": "create",
      "ranges": [{ "startOffset": 658, "endOffset": 1901, "count": 0 }],
      "isBlockCoverage": false
    },
    {
      "functionName": "getSegments",
      "ranges": [{ "startOffset": 1937, "endOffset": 1999, "count": 0 }],
      "isBlockCoverage": false
    },
    {
      "functionName": "getPath",
      "ranges": [{ "startOffset": 2042, "endOffset": 2087, "count": 0 }],
      "isBlockCoverage": false
    },
    {
      "functionName": "getFinalSegment",
      "ranges": [{ "startOffset": 2143, "endOffset": 2218, "count": 0 }],
      "isBlockCoverage": false
    },
    {
      "functionName": "getParentPath",
      "ranges": [{ "startOffset": 2287, "endOffset": 2496, "count": 0 }],
      "isBlockCoverage": false
    },
    {
      "functionName": "isParentOf",
      "ranges": [{ "startOffset": 2561, "endOffset": 2752, "count": 0 }],
      "isBlockCoverage": false
    },
    {
      "functionName": "getDepth",
      "ranges": [{ "startOffset": 2813, "endOffset": 2862, "count": 0 }],
      "isBlockCoverage": false
    },
    {
      "functionName": "equals",
      "ranges": [{ "startOffset": 2907, "endOffset": 2979, "count": 0 }],
      "isBlockCoverage": false
    },
    {
      "functionName": "PropertyPathNavigator",
      "ranges": [{ "startOffset": 3210, "endOffset": 3225, "count": 20 }],
      "isBlockCoverage": true
    },
    {
      "functionName": "create",
      "ranges": [{ "startOffset": 3294, "endOffset": 3384, "count": 20 }],
      "isBlockCoverage": true
    },
    {
      "functionName": "navigate",
      "ranges": [{ "startOffset": 3503, "endOffset": 4768, "count": 0 }],
      "isBlockCoverage": false
    },
    {
      "functionName": "assign",
      "ranges": [{ "startOffset": 4894, "endOffset": 6406, "count": 0 }],
      "isBlockCoverage": false
    },
    {
      "functionName": "pathExists",
      "ranges": [{ "startOffset": 6460, "endOffset": 6700, "count": 0 }],
      "isBlockCoverage": false
    },
    {
      "functionName": "getPathType",
      "ranges": [{ "startOffset": 6750, "endOffset": 7104, "count": 0 }],
      "isBlockCoverage": false
    },
    {
      "functionName": "isNavigationSuccess",
      "ranges": [{ "startOffset": 7169, "endOffset": 7245, "count": 0 }],
      "isBlockCoverage": false
    },
    {
      "functionName": "isPathNotFound",
      "ranges": [{ "startOffset": 7253, "endOffset": 7329, "count": 0 }],
      "isBlockCoverage": false
    },
    {
      "functionName": "isTypeMismatch",
      "ranges": [{ "startOffset": 7337, "endOffset": 7413, "count": 0 }],
      "isBlockCoverage": false
    },
    {
      "functionName": "isAssignmentSuccess",
      "ranges": [{ "startOffset": 7421, "endOffset": 7497, "count": 0 }],
      "isBlockCoverage": false
    },
    {
      "functionName": "isPathCreated",
      "ranges": [{ "startOffset": 7505, "endOffset": 7579, "count": 0 }],
      "isBlockCoverage": false
    },
    {
      "functionName": "isTypeConflict",
      "ranges": [{ "startOffset": 7587, "endOffset": 7663, "count": 0 }],
      "isBlockCoverage": false
    }
  ]
}
